urban_metagenomics_tutorial/__init__.py
urban_metagenomics_tutorial/cli.py
urban_metagenomics_tutorial/qc.py
urban_metagenomics_tutorial-0.1.0.dist-info/METADATA
urban_metagenomics_tutorial-0.1.0.dist-info/RECORD
urban_metagenomics_tutorial-0.1.0.dist-info/WHEEL
urban_metagenomics_tutorial-0.1.0.dist-info/entry_points.txt
urban_metagenomics_tutorial-0.1.0.dist-info/top_level.txt
